LICENSE.txt
README.md
setup.py
criteo_marketing_transition/__init__.py
criteo_marketing_transition/api_client.py
criteo_marketing_transition/configuration.py
criteo_marketing_transition/exceptions.py
criteo_marketing_transition/rest.py
criteo_marketing_transition.egg-info/PKG-INFO
criteo_marketing_transition.egg-info/SOURCES.txt
criteo_marketing_transition.egg-info/dependency_links.txt
criteo_marketing_transition.egg-info/requires.txt
criteo_marketing_transition.egg-info/top_level.txt
criteo_marketing_transition/api/__init__.py
criteo_marketing_transition/api/advertiser_api.py
criteo_marketing_transition/api/analytics_api.py
criteo_marketing_transition/api/audience_api.py
criteo_marketing_transition/api/campaign_api.py
criteo_marketing_transition/api/category_api.py
criteo_marketing_transition/api/o_auth_api.py
criteo_marketing_transition/models/__init__.py
criteo_marketing_transition/models/ad_set_delivery_limitations.py
criteo_marketing_transition/models/ad_set_frequency_capping.py
criteo_marketing_transition/models/ad_set_geo_location.py
criteo_marketing_transition/models/ad_set_search_filter.py
criteo_marketing_transition/models/ad_set_targeting.py
criteo_marketing_transition/models/ad_set_targeting_rule.py
criteo_marketing_transition/models/audience.py
criteo_marketing_transition/models/audience_attributes.py
criteo_marketing_transition/models/audience_error.py
criteo_marketing_transition/models/audience_name_description.py
criteo_marketing_transition/models/audience_warning.py
criteo_marketing_transition/models/basic_audience_definition.py
criteo_marketing_transition/models/bid_message.py
criteo_marketing_transition/models/campaign_bid_change_request.py
criteo_marketing_transition/models/campaign_bid_change_response.py
criteo_marketing_transition/models/campaign_bid_change_response_message_with_details.py
criteo_marketing_transition/models/campaign_bid_message.py
criteo_marketing_transition/models/campaign_message.py
criteo_marketing_transition/models/category_bid_change_request.py
criteo_marketing_transition/models/category_bid_message.py
criteo_marketing_transition/models/category_message.py
criteo_marketing_transition/models/category_update_error.py
