Metadata-Version: 2.1
Name: criteo-marketing-transition
Version: 1.0.3
Summary: Criteo Marketing Transition SDK
Home-page: https://github.com/criteo/criteo-python-marketing-transition-sdk
Author: Criteo
Author-email: 
License: UNKNOWN
Keywords: Criteo,OpenAPI-Generator,Criteo Marketing Transition SDK
Platform: UNKNOWN
Classifier: Development Status :: 4 - Beta
Classifier: Intended Audience :: Developers
Classifier: License :: OSI Approved :: Apache Software License
Classifier: Natural Language :: English
Classifier: Operating System :: OS Independent
Classifier: Topic :: Software Development :: Libraries
Classifier: Programming Language :: Python :: 2.7
Classifier: Programming Language :: Python :: 3.5
Classifier: Programming Language :: Python :: 3.7
Classifier: Programming Language :: Python :: 3.8
Requires-Python: >=2.7, !=3.0.*, !=3.1.*, !=3.2.*, !=3.3.*, !=3.4.*, <4
